Metadata-Version: 1.0
Name: django-sha2
Version: 0.4
Summary: Enable strong password hashes (bcrypt+hmac or SHA-2) in Django by default.
Home-page: http://github.com/fwenzel/django-sha2
Author: Fred Wenzel
Author-email: fwenzel@mozilla.com
License: BSD
Platform: UNKNOWN
Classifier: Development Status :: 4 - Beta
Classifier: Environment :: Web Environment
Classifier: Environment :: Web Environment :: Mozilla
Classifier: Framework :: Django
Classifier: Intended Audience :: Developers
Classifier: License :: OSI Approved :: BSD License
Classifier: Operating System :: OS Independent
Classifier: Programming Language :: Python
Classifier: Topic :: Software Development :: Libraries :: Python Modules
